{
    "Michigan" : {"grade": "A+"},
    "California" : {"grade": "A+"},
    "Arizona" : {"grade": "D+"},
    "Florida" : {"grade": "A"},
    "Georgia" : {"grade": "A"},
    "Mississippi" : {"grade": "A"},
    "Nevada" : {"grade": "A"},
    "Oklahoma" : {"grade": "A"},
    "Tennessee" : {"grade": "A"},
    "Wisconsin" : {"grade": "A"},
    "Texas" : {"grade": "B+"},
    "District of Columbia" : {"grade": "B"},
    "Missouri" : {"grade": "B"},
    "North Carolina" : {"grade": "B"},
    "Washington" : {"grade": "B"},
    "Wyoming" : {"grade": "B"},
    "Idaho" : {"grade": "C"},
    "Kansas" : {"grade": "C"},
    "Louisiana" : {"grade": "C"},
    "South Dakota" : {"grade": "C"},
    "Utah" : {"grade": "C"},
    "Connecticut" : {"grade": "D+"},
    "Kentucky" : {"grade": "D+"},
    "Ohio" : {"grade": "D+"},
    "Alabama" : {"grade": "D"},
    "Iowa" : {"grade": "D"},
    "Minnesota" : {"grade": "D"},
    "Nebraska" : {"grade": "D"},
    "New Jersey" : {"grade": "D"},
    "New Mexico" : {"grade": "D"},
    "North Dakota" : {"grade": "D"},
    "Oregon" : {"grade": "F"},
    "Rhode Island" : {"grade": "D"},
    "South Carolina" : {"grade": "D"},
    "Alaska" : {"grade": "F"},
    "Arkansas" : {"grade": "F"},
    "Colorado" : {"grade": "F"},
    "Delaware" : {"grade": "F"},
    "Hawaii" : {"grade": "F"},
    "Illinois" : {"grade": "F"},
    "Indiana" : {"grade": "F"},
    "Maine" : {"grade": "F"},
    "Maryland" : {"grade": "F"},
    "Massachusetts" : {"grade": "F"},
    "Montana" : {"grade": "F"},
    "New Hampshire" : {"grade": "F"},
    "New York" : {"grade": "F"},
    "Pennsylvania" : {"grade": "F"},
    "Vermont" : {"grade": "F"},
    "Virginia" : {"grade": "F"},
    "West Virginia" : {"grade": "F"}
}